AUTHORS.rst
CONTRIBUTING.rst
HISTORY.rst
LICENSE
MANIFEST.in
README.rst
setup.cfg
setup.py
docs/Makefile
docs/authors.rst
docs/conf.py
docs/contributing.rst
docs/history.rst
docs/index.rst
docs/installation.rst
docs/make.bat
docs/readme.rst
docs/usage.rst
tests/test_collection_tools.py
tests/test_string_tools.py
tests/test_toolspy.py
toolspy/__init__.py
toolspy/cli.py
toolspy/code_inspection_tools.py
toolspy/collection_tools.py
toolspy/csv_xl_tools.py
toolspy/datetime_tools.py
toolspy/filesystem_tools.py
toolspy/math_tools.py
toolspy/string_tools.py
toolspy/toolspy.py
toolspy/web_tools.py
toolspy.egg-info/PKG-INFO
toolspy.egg-info/SOURCES.txt
toolspy.egg-info/dependency_links.txt
toolspy.egg-info/entry_points.txt
toolspy.egg-info/not-zip-safe
toolspy.egg-info/requires.txt
toolspy.egg-info/top_level.txt