Metadata-Version: 1.1
Name: toolspy
Version: 0.3.5
Summary: A collection of python utilities
Home-page: https://github.com/SuryaSankar/toolspy
Author: Surya Sankar
Author-email: suryashankar.m@gmail.com
License: MIT license
Keywords: toolspy
Platform: UNKNOWN
Classifier: Development Status :: 2 - Pre-Alpha
Classifier: Intended Audience :: Developers
Classifier: License :: OSI Approved :: MIT License
Classifier: Natural Language :: English
Classifier: Programming Language :: Python :: 2
Classifier: Programming Language :: Python :: 2.7
